zilonis
