Metadata-Version: 2.1
Name: zilonis
Version: 1.11
Summary: Consumo Privado de API Cotizador
Home-page: UNKNOWN
Author: Alejandro Maldonado
Author-email: alejandro.maldonado@gonet.us
License: UNKNOWN
Platform: UNKNOWN
